{
  "phase": "12A",
  "step": "A2",
  "type": "prod-passive-baseline",
  "source": "nginx access logs via promtail-prod -> staging Loki",
  "prod_host": "178.104.108.108",
  "nginx_vhosts": ["satrank.dev", "api.satrank.dev"],
  "window": {
    "start_utc": "2026-04-21T08:30:35Z",
    "end_utc":   "2026-04-21T09:00:35Z",
    "duration_seconds": 1800
  },
  "aggregates": {
    "total_requests": 6,
    "avg_rps": 0.0033,
    "peak_1m_count": 3,
    "peak_1m_rps": 0.05,
    "error_log_lines": 0
  },
  "status_distribution": {
    "200": 1,
    "301": 1,
    "404": 3,
    "400": 1,
    "parser_miss": 1
  },
  "method_distribution": {
    "GET": 4,
    "HEAD": 1,
    "parser_miss": 1
  },
  "file_distribution": {
    "/var/log/nginx/access.log": 6,
    "/var/log/nginx/satrank.access.log": 0
  },
  "request_samples": [
    { "t": "2026-04-21T08:32:39Z", "src": "167.99.233.241", "req": "GET /",             "status": 301, "note": "http->https redirect" },
    { "t": "2026-04-21T08:32:40Z", "src": "167.99.233.241", "req": "GET /",             "status": 200, "note": "follow-up after redirect, served landing (6.8 kB)" },
    { "t": "2026-04-21T08:53:40Z", "src": "185.12.59.117",  "req": "GET /Dr0v",         "status": 404, "note": "scan/bot path" },
    { "t": "2026-04-21T08:55:19Z", "src": "185.242.226.114","req": "<TLS noise on :80>", "status": 400, "note": "TLS handshake sent to HTTP port, nginx bad-request" },
    { "t": "2026-04-21T08:55:48Z", "src": "34.158.104.72",  "req": "GET /api/decide",   "status": 404, "note": "external probe UA='node', no trailing slash vs /api/decide route miss" },
    { "t": "2026-04-21T08:55:48Z", "src": "34.158.104.72",  "req": "HEAD /api/decide",  "status": 404, "note": "paired with the GET above" }
  ],
  "interpretation": {
    "organic_user_traffic": "none observed in the 30-min window",
    "scanner_traffic":      "3 of 6 hits (scan of /Dr0v, TLS noise, /api/decide probe burst)",
    "legitimate_hits":      "1 visitor on the landing page (1x 301+200)",
    "confirms_assumption":  "baseline RPS ~= 0 as expected for pre-launch prod; 30-min window sufficient to confirm"
  },
  "methodology_notes": {
    "no_prom_scrape_of_prod": "by design (tunnel rejected); prod is observed via nginx access logs only. Internal state (cache hits, LND inflight, DB p95) is not visible at this step.",
    "request_time_distribution": "nginx access_log format does not include $request_time on the default 'combined' format; promtail histogram metric is emitted but not scraped back (prod has no Prometheus exporter in scope). Latency at idle is not sampled in A2; A6 smoke test will provide iso-charge prod latency.",
    "prod_metrics_endpoint": "/metrics is exposed and auth-bypassed from localhost (src/app.ts:408-416); unused in Phase 12A per scope decision.",
    "window_length_reduction": "30 min instead of 2 h; justified by near-zero baseline observed and confirmed on-the-fly."
  },
  "downstream_use": {
    "A6_smoke_delta":  "subtract this baseline from A6 traffic to isolate smoke impact; given baseline is ~0, A6 numbers are effectively the smoke-only signal.",
    "A7_report": "feed the 'organic user load = 0' assumption into the report palier discussion (first user = rupture point at 1x is a real risk only under burst scenarios)."
  }
}
